kubragen/__init__.py
kubragen/builder.py
kubragen/configfile.py
kubragen/consts.py
kubragen/data.py
kubragen/exception.py
kubragen/helper.py
kubragen/jsonpatch.py
kubragen/kdata.py
kubragen/kdatahelper.py
kubragen/kresource.py
kubragen/kubragen.py
kubragen/merger.py
kubragen/object.py
kubragen/option.py
kubragen/options.py
kubragen/output.py
kubragen/provider.py
kubragen/py.typed
kubragen/types.py
kubragen/util.py
kubragen/yaml.py
kubragen/cmd/yamltodict.py
kubragen/private/__init__.py
kubragen/private/jsonpatch.py
kubragen/private/merger.py
kubragen/private/options.py
kubragen/private/yaml.py
kubragen/tests/__init__.py
kubragen/tests/test_builder.py
kubragen/tests/test_data.py
kubragen/tests/test_jsonpatch.py
kubragen/tests/test_kdata.py
kubragen/tests/test_options.py
kubragen/tests/test_provider.py
kubragen-0.8.4.dist-info/LICENSE
kubragen-0.8.4.dist-info/METADATA
kubragen-0.8.4.dist-info/WHEEL
kubragen-0.8.4.dist-info/top_level.txt
kubragen-0.8.4.dist-info/RECORD
